{
  "home": "",
  "adminHome": "/admin",
  "adminSetting": "/admin/setting",
  "adminBankDetail": "/admin/admin-bank-details",
  "adminUsersBalance": "/admin/user-balance",
  "adminUsers": "/admin/user-management",
  "adminUsersPermission": "/admin/user-permission",
  "adminUsersSecession": "/admin/user-secession",
  "adminUsersSession": "/admin/user-session-history",
  "adminSecurityKyc": "/admin/user-kyc-management",
  "adminSecurityKycCertification": "/admin/auth-kyc-certification",
  "adminUsersAffiliate": "/admin/user-affiliate-management",
  "adminTransactionWithdrawals": "/admin/transaction-withdrawals",
  "adminWalletDeposits": "/admin/transaction-deposits",
  "adminTransactionsFees": "/admin/transaction-fee-management",
  "adminAdvert": "/admin/adverts",
  "adminOrder": "/admin/orders",
  "adminTradeHistory": "/admin/p2p-trade-history",
  "adminTradeDispute": "/admin/p2p-disputes",
  "adminChatHistory": "/admin/chat-history",
  "adminChatMessenger": "/admin/chat-messenger",
  "adminSecurityHome": "/admin/auth-security-management",
  "adminSupport": "/admin/support",
  "adminSupportDisputes": "/admin/support-disputes",
  "adminCurrency": "/admin/currency-management",
  "adminLogin": "/admin/login",
  "auth": "/auth",
  "authLogin": "/auth/login",
  "authRegister": "/auth/register",
  "authChangePassword": "/auth/changePassword",
  "authForgotPassword": "/auth/forgot",
  "authVerify": "/auth/verify",
  "authVerifyEmail": "/auth/verify/email",
  "authVerifyOTP": "/auth/verify/otp",
  "authVerifyPhone": "/auth/verify/phone",
  "order": "/order",
  "orderByUser": "/order/user",
  "advert": "/advert",
  "advertByUser": "/advert/user",
  "advertCreate": "/advert/create",
  "wallet": "/wallet",
  "walletHistory": "/wallet/history",
  "affiliate": "/affiliate",
  "support": "/support",
  "me": "/me",
  "payment": "/payment",
  "addPayment": "/payment/add"
}